[
    {
        "id": 1,
        "nombre": "Claudio",
        "apellido": "Valverde",
        "titulo": "",
        "fotoUrl": "",
        "descripcion": "",
        "estado": "actual"
    },
    {
        "id": 2,
        "nombre": "Betina",
        "apellido": "Agaras",
        "titulo": "Dra. en Ciencia y Tecnología UNQ (Microbiología agrícola)",
        "fotoUrl": "./imgs/investigadores/Foto BA nueva.jpg",
        "descripcion": "Lorem ipsum dolor sit amet, consectetur adipiscing elit. Nunc malesuada ultrices arcu quis posuere. Mauris posuere lobortis quam, eu iaculis risus tristique vestibulum. Fusce consectetur massa sed venenatis efficitur. Phasellus mattis leo quis felis interdum, ut aliquam purus fringilla. Integer gravida eros eu dui eleifend semper. Proin non erat leo. Cras elementum nulla at dolor pellentesque, sed gravida ligula luctus. Sed elementum lacus risus, sed consequat lacus efficitur eget. Phasellus ac urna maximus, sodales orci quis, efficitur enim. Sed porta risus eget lorem malesuada, non lacinia nunc tincidunt. Vivamus dolor tellus, porta et tellus in, rutrum convallis est. Curabitur ultrices sapien vitae mauris porta, id scelerisque felis tempor.",
        "estado": "actual"
    },
    {
        "id": 3,
        "nombre": "Antonio",
        "apellido": "Lagares Jr.",
        "titulo": "",
        "fotoUrl": "",
        "descripcion": "",
        "estado": "actual"
    },
    {
        "id": 4,
        "nombre": "Patricio",
        "apellido":"Sobrero",
        "titulo": "",
        "fotoUrl": "",
        "descripcion": "",
        "estado": "actual"
    },
    {
        "id": 5,
        "nombre": "Melina",
        "apellido":"Martins",
        "titulo": "",
        "fotoUrl": "",
        "descripcion": "",
        "estado": "actual"
    },
    {
        "id": 6,
        "nombre": "Yanina",
        "apellido": "Magaldi",
        "titulo": "",
        "fotoUrl": "",
        "descripcion": "",
        "estado": "actual"
    },
    {
        "id": 7,
        "nombre": "Fernanda",
        "apellido": "Coelho",
        "titulo": "",
        "fotoUrl": "",
        "descripcion": "",
        "estado": "actual"
    },
    {
        "id": 8,
        "nombre": "Melani",
        "apellido": "Lorch",
        "titulo": "",
        "fotoUrl": "",
        "descripcion": "",
        "estado": "actual"
    }
]